db_shifter/__init__.py
db_shifter/__main__.py
db_shifter/main.py
db_shifter-0.1.9.dist-info/METADATA
db_shifter-0.1.9.dist-info/WHEEL
db_shifter-0.1.9.dist-info/entry_points.txt
db_shifter-0.1.9.dist-info/top_level.txt
db_shifter-0.1.9.dist-info/RECORD
