Metadata-Version: 2.4
Name: db-shifter
Version: 0.1.9
Summary: A smart tool to sync missing rows between two PostgreSQL databases.
Home-page: https://github.com/goodness5/db-shifter
Author: superman
Author-email: goodnesskolapo@gmail.com
Project-URL: Changelog, https://github.com/goodness5/db-shifter/blob/master/CHANGELOG.md
Project-URL: Source, https://github.com/goodness5/db-shifter
Project-URL: Tracker, https://github.com/goodness5/db-shifter/issues
Classifier: Programming Language :: Python :: 3
Classifier: License :: OSI Approved :: MIT License
Classifier: Operating System :: OS Independent
Requires-Python: >=3.7
Requires-Dist: psycopg2-binary
Dynamic: author
Dynamic: author-email
Dynamic: classifier
Dynamic: description
Dynamic: description-content-type
Dynamic: home-page
Dynamic: project-url
Dynamic: requires-dist
Dynamic: requires-python
Dynamic: summary
